README.md
setup.cfg
setup.py
damnboleto/__init__.py
damnboleto/constants.py
damnboleto/exceptions.py
damnboleto/extractor.py
damnboleto.egg-info/PKG-INFO
damnboleto.egg-info/SOURCES.txt
damnboleto.egg-info/dependency_links.txt
damnboleto.egg-info/not-zip-safe
damnboleto.egg-info/requires.txt
damnboleto.egg-info/top_level.txt
tests/__init__.py
tests/test_extractor.py