Metadata-Version: 1.1
Name: damnboleto
Version: 0.2.1
Summary: Extract boleto's data
Home-page: https://github.com/marquesds/damnboleto
Author: Lucas Marques
Author-email: lucasmarquesds@gmail.com
License: UNKNOWN
Download-URL: https://github.com/marquesds/damnboleto/archive/0.2.1.zip
Keywords: boleto,extractor,pdf
Platform: UNKNOWN
Classifier: Programming Language :: Python :: 3.6
